jupyterlab_unfold/__init__.py
jupyterlab_unfold/_version.py
jupyterlab_unfold-0.3.4.data/data/share/jupyter/labextensions/jupyterlab-unfold/build_log.json
jupyterlab_unfold-0.3.4.data/data/share/jupyter/labextensions/jupyterlab-unfold/package.json
jupyterlab_unfold-0.3.4.data/data/share/jupyter/labextensions/jupyterlab-unfold/schemas/jupyterlab-unfold/jupyterlab-unfold-settings.json
jupyterlab_unfold-0.3.4.data/data/share/jupyter/labextensions/jupyterlab-unfold/schemas/jupyterlab-unfold/package.json.orig
jupyterlab_unfold-0.3.4.data/data/share/jupyter/labextensions/jupyterlab-unfold/schemas/jupyterlab-unfold/plugin.json
jupyterlab_unfold-0.3.4.data/data/share/jupyter/labextensions/jupyterlab-unfold/static/lib_index_js.6dfa3f02b6bc6bc819cd.js
jupyterlab_unfold-0.3.4.data/data/share/jupyter/labextensions/jupyterlab-unfold/static/lib_index_js.6dfa3f02b6bc6bc819cd.js.map
jupyterlab_unfold-0.3.4.data/data/share/jupyter/labextensions/jupyterlab-unfold/static/remoteEntry.97a21993f229c000ae16.js
jupyterlab_unfold-0.3.4.data/data/share/jupyter/labextensions/jupyterlab-unfold/static/remoteEntry.97a21993f229c000ae16.js.map
jupyterlab_unfold-0.3.4.data/data/share/jupyter/labextensions/jupyterlab-unfold/static/style.js
jupyterlab_unfold-0.3.4.data/data/share/jupyter/labextensions/jupyterlab-unfold/static/style_index_js.3b480e1669be0c610bca.js
jupyterlab_unfold-0.3.4.data/data/share/jupyter/labextensions/jupyterlab-unfold/static/style_index_js.3b480e1669be0c610bca.js.map
jupyterlab_unfold-0.3.4.data/data/share/jupyter/labextensions/jupyterlab-unfold/install.json
jupyterlab_unfold-0.3.4.dist-info/METADATA
jupyterlab_unfold-0.3.4.dist-info/WHEEL
jupyterlab_unfold-0.3.4.dist-info/licenses/LICENSE
jupyterlab_unfold-0.3.4.dist-info/RECORD
