Metadata-Version: 2.4
Name: jupyterlab-unfold
Version: 0.3.4
Dynamic: Keywords
Summary: A vscode-like file browser
Project-URL: Homepage, https://github.com/jupyterlab-contrib/jupyterlab-unfold
Project-URL: Bug Tracker, https://github.com/jupyterlab-contrib/jupyterlab-unfold/issues
Project-URL: Repository, https://github.com/jupyterlab-contrib/jupyterlab-unfold.git
Author-email: Martin Renou <martin.renou@gmail.com>
License: BSD 3-Clause License
License-File: LICENSE
Classifier: Framework :: Jupyter
Classifier: Framework :: Jupyter :: JupyterLab
Classifier: Framework :: Jupyter :: JupyterLab :: 4
Classifier: Framework :: Jupyter :: JupyterLab :: Extensions
Classifier: Framework :: Jupyter :: JupyterLab :: Extensions :: Prebuilt
Classifier: License :: OSI Approved :: BSD License
Classifier: Programming Language :: Python
Classifier: Programming Language :: Python :: 3
Classifier: Programming Language :: Python :: 3.8
Classifier: Programming Language :: Python :: 3.9
Classifier: Programming Language :: Python :: 3.10
Classifier: Programming Language :: Python :: 3.11
Requires-Python: >=3.8
